tfc_client/__init__.py
tfc_client/api_caller.py
tfc_client/enums.py
tfc_client/exception.py
tfc_client/tfc_client.py
tfc_client/tfc_object.py
tfc_client/tfc_objects.py
tfc_client/util.py
tfc_client/models/__init__.py
tfc_client/models/apply.py
tfc_client/models/configuration_version.py
tfc_client/models/data.py
tfc_client/models/notification_configuration.py
tfc_client/models/oauth_token.py
tfc_client/models/organization.py
tfc_client/models/plan.py
tfc_client/models/relationship.py
tfc_client/models/run.py
tfc_client/models/ssh_key.py
tfc_client/models/var.py
tfc_client/models/workspace.py
tfc_client-0.7.3.dist-info/LICENSE
tfc_client-0.7.3.dist-info/METADATA
tfc_client-0.7.3.dist-info/WHEEL
tfc_client-0.7.3.dist-info/top_level.txt
tfc_client-0.7.3.dist-info/RECORD
