Metadata-Version: 2.1
Name: tfc-client
Version: 0.7.3
Summary: A developer friendly Terraform Cloud API client
Home-page: https://github.com/adeo/iwc-tfc-client
Author: Alexandre Dath for ADEO
Author-email: alex.dath@gmail.com
License: MIT
Keywords: API Terraform TFC
Platform: UNKNOWN
Classifier: Development Status :: 4 - Beta
Classifier: Programming Language :: Python :: 3
Classifier: Programming Language :: Python :: 3.7
Classifier: Topic :: Software Development :: Libraries
Classifier: License :: OSI Approved :: MIT License
Classifier: Operating System :: OS Independent
Requires-Python: >=3.7
Requires-Dist: requests
Requires-Dist: pydantic (>=0.32.2)
Requires-Dist: pydantic[email]
Requires-Dist: email-validator (>=1.0.3)
Requires-Dist: idna (>=2.0.0)
Requires-Dist: dnspython (>=1.15.0)
Requires-Dist: inflection
Provides-Extra: dev
Requires-Dist: black ; extra == 'dev'
Requires-Dist: twine ; extra == 'dev'
Requires-Dist: wheel ; extra == 'dev'
Provides-Extra: test
Requires-Dist: pytest ; extra == 'test'
Requires-Dist: coverage ; extra == 'test'
Requires-Dist: pytest-cov ; extra == 'test'
